{
  "project_info": {
    "project_number": "830292726614",
    "firebase_url": "https://quarantine-tracker-2a14a.firebaseio.com",
    "project_id": "quarantine-tracker-2a14a",
    "storage_bucket": "quarantine-tracker-2a14a.appspot.com"
  },
  "client": [
    {
      "client_info": {
        "mobilesdk_app_id": "1:830292726614:android:e7c48b229a6e1c04d6fcf7",
        "android_client_info": {
          "package_name": "com.ak86.quarantinetracker"
        }
      },
      "oauth_client": [
        {
          "client_id": "830292726614-mnjjhclr8i5um0joep3ot7gtnv2hmen2.apps.googleusercontent.com",
          "client_type": 1,
          "android_info": {
            "package_name": "com.ak86.quarantinetracker",
            "certificate_hash": "8f4cfdd4c3f6ff125c002a2cc0a6323bf9a8a9bc"
          }
        },
        {
          "client_id": "830292726614-aemg8jh6gme6528qff8j81tu4bk17gt0.apps.googleusercontent.com",
          "client_type": 3
        }
      ],
      "api_key": [
        {
          "current_key": "AIzaSyAt55eSWaqFwE6t-b1YH5eThCOgilw0l4w"
        }
      ],
      "services": {
        "appinvite_service": {
          "other_platform_oauth_client": [
            {
              "client_id": "830292726614-aemg8jh6gme6528qff8j81tu4bk17gt0.apps.googleusercontent.com",
              "client_type": 3
            }
          ]
        }
      }
    }
  ],
  "configuration_version": "1"
}